.gitignore
Makefile
README.md
dx.py
setup.py
tox.ini
docs/logo.jpg
docs/logo.xcf
dspipe/__init__.py
dspipe/_version.py
dspipe/es_pipeline.py
dspipe/pipeline.py
dspipe.egg-info/PKG-INFO
dspipe.egg-info/SOURCES.txt
dspipe.egg-info/dependency_links.txt
dspipe.egg-info/requires.txt
dspipe.egg-info/top_level.txt
tests/pipeline_test.py