Metadata-Version: 2.1
Name: dspipe
Version: 0.4.0
Summary: dspipe: Easy to use data science pipes
Home-page: https://github.com/thoppe/dspipe
Author: Travis Hoppe
Author-email: travis.hoppe+dspipe@gmail.com
License: CC0
Keywords: datascience
Classifier: Development Status :: 5 - Production/Stable
Classifier: Intended Audience :: Developers
Classifier: Intended Audience :: Science/Research
Classifier: Intended Audience :: Healthcare Industry
Classifier: Intended Audience :: Education
Classifier: Intended Audience :: Financial and Insurance Industry
Classifier: Topic :: Utilities
Classifier: License :: OSI Approved :: MIT License
Classifier: Programming Language :: Python :: 3.7
Requires-Dist: joblib
Requires-Dist: wasabi
Requires-Dist: tqdm
